sqlalchemy_toolkit/__init__.py
sqlalchemy_toolkit/entity.py
sqlalchemy_toolkit/ext/fastapi/__init__.py
sqlalchemy_toolkit/ext/fastapi/middleware.py
sqlalchemy_toolkit/manager.py
sqlalchemy_toolkit/py.typed
sqlalchemy_toolkit/repository.py
sqlalchemy_toolkit/session.py
sqlalchemy_toolkit-0.1.1.dist-info/LICENSE
sqlalchemy_toolkit-0.1.1.dist-info/METADATA
sqlalchemy_toolkit-0.1.1.dist-info/WHEEL
sqlalchemy_toolkit-0.1.1.dist-info/RECORD
