Metadata-Version: 2.1
Name: sqlalchemy-toolkit
Version: 0.1.1
Summary: Simplify SQLAlchemy 2.0+ usage.
Home-page: https://github.com/javalce/sqlalchemy-toolkit
License: MIT
Keywords: sqlalchemy
Author: Javier Valero Cejudo
Author-email: javalce29@gmail.com
Requires-Python: >=3.8,<4.0
Classifier: License :: OSI Approved :: MIT License
Classifier: Programming Language :: Python :: 3
Classifier: Programming Language :: Python :: 3.8
Classifier: Programming Language :: Python :: 3.9
Classifier: Programming Language :: Python :: 3.10
Classifier: Programming Language :: Python :: 3.11
Classifier: Programming Language :: Python :: 3.12
Requires-Dist: sqlalchemy (>=2.0.0,<2.1.0)
Project-URL: Repository, https://github.com/javalce/sqlalchemy-toolkit
